{"cls":"transform","insid":-11234,"name":"tank02","localRotate":{"cls":"quaternion","x":0,"y":0,"z":0,"w":1},"localTranslate":{"cls":"vector3","x":0,"y":0,"z":0},"localScale":{"cls":"vector3","x":1,"y":1,"z":1},"gameObject":{"cls":"gameObject","layer":0},"children":[{"cls":"transform","insid":-1874,"name":"enemy_down","localRotate":{"cls":"quaternion","x":2.006696e-7,"y":0,"z":0,"w":1},"localTranslate":{"cls":"vector3","x":0,"y":0.1085591,"z":0},"localScale":{"cls":"vector3","x":0.036,"y":0.02713483,"z":0.036},"gameObject":{"cls":"gameObject","layer":0,"components":[{"cls":"meshFilter","mesh":{"cls":"mesh","value":"model_tank02.FBX_enemy_down.mesh.bin"}},{"cls":"meshRenderer","materials":[{"cls":"material","value":"tank02.mat.json"}],"lightmapIndex":-1}]}},{"cls":"transform","insid":-12620,"name":"tank_up","localRotate":{"cls":"quaternion","x":0,"y":0,"z":0,"w":1},"localTranslate":{"cls":"vector3","x":0.00003630338,"y":0.2982937,"z":-0.01724596},"localScale":{"cls":"vector3","x":1,"y":1,"z":1},"gameObject":{"cls":"gameObject","layer":0},"children":[{"cls":"transform","insid":-1878,"name":"enemy_up","localRotate":{"cls":"quaternion","x":8.146034e-8,"y":-4.470348e-8,"z":1.68751e-15,"w":1},"localTranslate":{"cls":"vector3","x":0,"y":0,"z":0},"localScale":{"cls":"vector3","x":0.036,"y":0.036,"z":0.036},"gameObject":{"cls":"gameObject","layer":0,"components":[{"cls":"meshFilter","mesh":{"cls":"mesh","value":"model_tank02.FBX_enemy_up.mesh.bin"}},{"cls":"meshRenderer","materials":[{"cls":"material","value":"tank02.mat.json"}],"lightmapIndex":-1}]}},{"cls":"transform","insid":-1876,"name":"enemy_front","localRotate":{"cls":"quaternion","x":8.146034e-8,"y":0,"z":0,"w":1},"localTranslate":{"cls":"vector3","x":-0.00003630338,"y":-0.01335225,"z":0.1060764},"localScale":{"cls":"vector3","x":0.036,"y":0.036,"z":0.036},"gameObject":{"cls":"gameObject","layer":0,"components":[{"cls":"meshFilter","mesh":{"cls":"mesh","value":"model_tank02.FBX_enemy_front.mesh.bin"}},{"cls":"meshRenderer","materials":[{"cls":"material","value":"tank02.mat.json"}],"lightmapIndex":-1}]}},{"cls":"transform","insid":-14942,"name":"slot","localRotate":{"cls":"quaternion","x":0,"y":0,"z":0,"w":1},"localTranslate":{"cls":"vector3","x":0,"y":-0.0138,"z":0.34},"localScale":{"cls":"vector3","x":1,"y":1,"z":1},"gameObject":{"cls":"gameObject","layer":0}}]}]}